nl/__init__.py
nl/newfoundland/__init__.py
nl/newfoundland/kgworkflow/__init__.py
nl/newfoundland/kgworkflow/generator/__init__.py
nl/newfoundland/kgworkflow/generator/iri/__init__.py
nl/newfoundland/kgworkflow/generator/iri/cli.py
nl/newfoundland/kgworkflow/generator/iri/config.py
nl/newfoundland/kgworkflow/generator/iri/discovery.py
nl/newfoundland/kgworkflow/generator/iri/enrichment.py
nl/newfoundland/kgworkflow/generator/iri/graph_loader.py
nl/newfoundland/kgworkflow/generator/iri/helpers.py
nl/newfoundland/kgworkflow/generator/iri/manchester.py
nl/newfoundland/kgworkflow/generator/iri/naming.py
nl/newfoundland/kgworkflow/generator/iri/qc.py
nl/newfoundland/kgworkflow/generator/iri/rendering.py
nl/newfoundland/kgworkflow/generator/iri/symbol_map.py
nl/newfoundland/kgworkflow/generator/iri/backends/__init__.py
nl/newfoundland/kgworkflow/generator/iri/backends/oxigraph_backend.py
nl/newfoundland/kgworkflow/generator/iri/backends/rdflib_backend.py
owl_iri_code_generator-0.8.21.dist-info/METADATA
owl_iri_code_generator-0.8.21.dist-info/WHEEL
owl_iri_code_generator-0.8.21.dist-info/entry_points.txt
owl_iri_code_generator-0.8.21.dist-info/top_level.txt
owl_iri_code_generator-0.8.21.dist-info/RECORD
