Metadata-Version: 2.4
Name: owl-iri-code-generator
Version: 0.8.21
Summary: Generate deterministic Python modules that expose OWL ontology IRIs as `rdflib.URIRef` symbols, with rich Manchester-style axiomatization and annotations embedded as comments. Includes a QC report, coverage diagnostics, and a persistent symbol map to keep names stable across runs.
Project-URL: Repository, https://github.com/spdrnl/owl-iri-code-generator
Requires-Python: >=3.11
Requires-Dist: oxigraph>=0.5.2
Requires-Dist: pyoxigraph>=0.5.2
Requires-Dist: rdflib>=7.4.0
Requires-Dist: oxrdflib>=0.4.0
